graphical_model_learning/__init__.py
graphical_model_learning/algorithms/__init__.py
graphical_model_learning/algorithms/covariance.py
graphical_model_learning/algorithms/nodewise.py
graphical_model_learning/algorithms/undirected.py
graphical_model_learning/algorithms/dag/__init__.py
graphical_model_learning/algorithms/dag/ges.py
graphical_model_learning/algorithms/dag/gsp.py
graphical_model_learning/algorithms/dag/gsp_new.py
graphical_model_learning/algorithms/dag/pcalg.py
graphical_model_learning/algorithms/dag/resit.py
graphical_model_learning/algorithms/difference/__init__.py
graphical_model_learning/algorithms/difference/_utils.py
graphical_model_learning/algorithms/difference/difference_dag.py
graphical_model_learning/algorithms/difference/difference_ug.py
graphical_model_learning/algorithms/mag/__init__.py
graphical_model_learning/algorithms/mag/gspo.py
graphical_model_learning/samplers/__init__.py
graphical_model_learning/samplers/minimal_imap_mcmc.py
graphical_model_learning/samplers/proposals/__init__.py
graphical_model_learning/samplers/proposals/transposition_proposers.py
graphical_model_learning/scores/__init__.py
graphical_model_learning/scores/gaussian_bge_score.py
graphical_model_learning/scores/gaussian_bic_score.py
graphical_model_learning/scores/gaussian_ibge_score.py
graphical_model_learning/scores/gaussian_interventional_bge_score.py
graphical_model_learning/scores/gaussian_likelihood.py
graphical_model_learning/scores/gaussian_monte_carlo_bge_score.py
graphical_model_learning/scores/monte_carlo_bge_score.py
graphical_model_learning/scores/monte_carlo_marginal_likelihood.py
graphical_model_learning/scores/sandbox_monte_carlo.py
graphical_model_learning/scores/score.py
graphical_model_learning/suffstats/__init__.py
graphical_model_learning/suffstats/gaussian_interventional_suffstat.py
graphical_model_learning/utils/__init__.py
graphical_model_learning/utils/core_utils.py
graphical_model_learning/utils/regression.py
graphical_model_learning-0.1a8.dist-info/LICENSE.txt
graphical_model_learning-0.1a8.dist-info/METADATA
graphical_model_learning-0.1a8.dist-info/WHEEL
graphical_model_learning-0.1a8.dist-info/top_level.txt
graphical_model_learning-0.1a8.dist-info/RECORD
